bingo_game/__init__.py
bingo_game/game.py
bingo_game-1.0.0.dist-info/LICENSE
bingo_game-1.0.0.dist-info/METADATA
bingo_game-1.0.0.dist-info/WHEEL
bingo_game-1.0.0.dist-info/entry_points.txt
bingo_game-1.0.0.dist-info/top_level.txt
bingo_game-1.0.0.dist-info/RECORD
