Metadata-Version: 2.1
Name: bingo_game
Version: 1.0.0
Summary: A simple Bingo game to play in the terminal.
Home-page: https://github.com/AromalShaji/python-bingo
Author: Your Name
Author-email: your.email@example.com
Classifier: Programming Language :: Python :: 3
Classifier: License :: OSI Approved :: MIT License
Classifier: Operating System :: OS Independent
Requires-Python: >=3.6
License-File: LICENSE
Requires-Dist: colorama>=0.4.6
